{
  "chunk_id": "PD_12B__chunk038",
  "source_file": "raw/practice_directions/PD_12B.md",
  "layer": "layer1",
  "chunk_index": 38,
  "total_chunks": 40,
  "token_count": 211,
  "text": "25.If the case progresses to court, parties will be required to tell a judge about the non-court dispute resolution methods they explored and why they were unsuccessful.\n\n\nCompliance with this Protocol\n\n\n26.If a judge finds that the Protocol has not been complied with, they may order that the gaps between court hearings must be used for the parties to undertake any of the steps described that may have been missed. Or the judge may order that the court proceedings are paused for the same purpose. A judge may, for example, order that parties attend a MIAM, or encourage a method of NCDR.\n\n\n27.The court also has the power to make costs orders. These can be made when court proceedings are ongoing, or when they come to an end. When deciding whether to order one party to pay some or all of the legal costs of another party, the court will take into account the parties’ conduct, including any failure to comply with this Protocol.\n\n\nDefinition of terms used in this Protocol\n\n\n28.A list of definitions used in this Protocol can be found below:",
  "metadata": {
    "source": "Family Procedure Rules – Practice Directions",
    "ref": "PD 12B",
    "title": "Practice Direction 12B – Child Arrangements Programme",
    "url": "https://www.justice.gov.uk/courts/procedure-rules/family/practice_directions/pd_part_12b",
    "status": "Active",
    "scraped": "2026-06-10",
    "licence": "Open Government Licence v3.0"
  }
}