{
  "chunk_id": "PD_36ZD__chunk010",
  "source_file": "raw/practice_directions/PD_36ZD.md",
  "layer": "layer1",
  "chunk_index": 10,
  "total_chunks": 14,
  "token_count": 468,
  "text": "10.5 In paragraph 8.6 for “attached to the Form C100” substitute “uploaded to the online system”.\n\n\n10.6 After paragraph 8.12 insert-\n\n\n“8.13    Where a party has agreed to the court sending documents to them by email, the documents referred to in paragraph 8.7, 8.8 or 8.12 may be sent or served by the court sending an email to the party, to the email address given for service in accordance with Practice Direction 6A, which-\n\n\n(a) contains a weblink to the online system, from which the document may be accessed and downloaded; or\n\n\n(b) attaches the document to be served.\n\n\n8.14 Where-\n\n\n(a) paragraph 8.13 applies; and\n\n\n(b) the person on whom the documents are being served, or to whom the documents are being sent, is unrepresented,\n\n\na letter confirming that such an email has been sent may be sent by the court to the postal address of the person to whom the email was sent, by first class post or other service which provides for delivery on the next business day.”.\n\n\n10.7 In paragraph 8.11, at the end insert-\n\n\n“The respondent(s) may send the forms to the court by post or by uploading them to the online system.”\n\n\n10.8 In paragraph 12.5 omit the words from after “safeguarding checks” to the end of the paragraph.\n\n\n10.9 In the Annex (Explanation of Terms), in the row relating to the term “File”, in the second column after “court office” insert-\n\n\n“or, where Practice Direction 36ZD applies, by-\n\n\n(i) uploading the document on the online system referred in that Practice Direction; or\n\n\n(ii) submitting the information via that online system.”\n\n\nModification of FPR Practice Direction 12B (Pilot), annexed to Practice Direction 36Z\n\n\n11.1 For paragraph 8.2 substitute-\n\n\n“8.2   Where the pilot scheme referred to in Practice Direction 36ZD applies-\n\n\n(a) an application for an enforcement order must be made on the relevant prescribed form and be uploaded on the online system referred to in Practice Direction 36ZD; and",
  "metadata": {}
}