{
  "chunk_id": "PD_36Z__chunk000",
  "source_file": "raw/practice_directions/PD_36Z.md",
  "layer": "layer1",
  "chunk_index": 0,
  "total_chunks": 48,
  "token_count": 494,
  "text": "---\nsource: Family Procedure Rules – Practice Directions\nref: PD 36Z\ntitle: Practice Direction 36Z – Pilot Scheme: private law reform: Investigative approach\nurl: https://www.justice.gov.uk/courts/procedure-rules/family/practice_directions/new-practice-direction-36z-pilot-scheme-private-law-reform-investigative-approach\nstatus: Active\nscraped: 2026-06-10\nlicence: Open Government Licence v3.0\n---\n\n# Practice Direction 36Z – Pilot Scheme: private law reform: Investigative approach\n\nThis Practice Direction supplements FPR Part 36, rule 36.2 (Transitional Arrangements and Pilot Schemes).\n\n\nScope and interpretation\n\n\n1.1 This Practice Direction is made under rule 36.2 and establishes a Pilot Scheme (referred to as “the Pilot Scheme”) to allow certain applications, and stages in proceedings relating to such applications, to follow a procedure different to that specified in the Family Procedure Rules 2010 (“the FPR”) and supporting Practice Directions.\n\n\n1.2 This Practice Direction comes into force on 21 February 2022.\n\n\n1.3 The Pilot Scheme applies where all of the following conditions are met-\n\n\n(a) the application is for-\n\n\n(i) a section 8 order;\n\n\n(ii) an enforcement order;\n\n\n(b) the application is started in the family court sitting at a location specified in paragraphs 14, 1.4A, 1.4B, 1.4C, 1.4D, 1.4E or 1.4F; and\n\n\n(c) in the case of-\n\n\n(i) an application started in a location of the family court specified in paragraph 1.4, the application is filed in the period commencing 21 February 2022 and ending at the end of 31 March 2027;\n\n\n(ii) an application started in a location of the family court specified in paragraph 1.4A, the application is filed in the period commencing 29 April 2024 and ending at the end of 31 March 2027;\n\n\n(iii) an application started in a location of the family court specified in paragraph 1.4B, the application is filed in the period commencing 28 May 2024 and ending at the end of 31 March 2027.",
  "metadata": {}
}