{
  "chunk_id": "PD_37A__chunk000",
  "source_file": "raw/practice_directions/PD_37A.md",
  "layer": "layer1",
  "chunk_index": 0,
  "total_chunks": 1,
  "token_count": 467,
  "text": "# Practice Direction 37A – Applications and Proceedings in Relation to Contempt of Court\n\nSee also Part 37\n\n\nPRACTICE DIRECTION 37A – APPLICATIONS AND PROCEEDINGS IN RELATION TO CONTEMPT OF COURT\n\n\nDirections for hearings of contempt proceedings\n\n\n1. Evidence adduced by defendant. Rule 37.7(3) provides that the court may not give any direction compelling the defendant to give evidence either orally or in writing. The court may, however, direct that, if the defendant wishes to adduce evidence in response to the contempt application, the defendant file and serve witness statements of the witnesses (including himself or herself) on which reliance is intended. Such statements may not be used against the defendant in the contempt application unless and until the defendant deploys them in support of the defendant’s case against the contempt application.\n\n\n2. Striking out and procedural defects.(1) On application by the defendant or on its own initiative, the court may strike out a\n\n\ncontempt application if it appears to the court—\n\n\n(a) that the application and the evidence served in support of it disclose no reasonable ground for alleging that the defendant is guilty of a contempt of court;\n\n\n(b) that the application is an abuse of the court’s process or, if made in existing proceedings, is otherwise likely to obstruct the just disposal of those proceedings; or\n\n\n(c) that there has been a failure to comply with a rule, practice direction or court order.\n\n\n(2) The court may waive any procedural defect in the commencement or conduct of a contempt application if satisfied that no injustice has been caused to the defendant by the defect.\n\n\nHearings and judgments in contempt proceedings\n\n\n3. Informing the defendant of right to appeal, etc. Paragraph (12) of rule 37.8 does not require the court to inform a defendant who has been acquitted of contempt of the right to appeal and the other matters listed in that paragraph.\n\n\n4. Responsibility of court for publication of judgments. While paragraph (13) of rule 37.8 makes the court responsible for the publication of transcripts of judgments in contempt proceedings, it does not require the court to publish a transcript of every judgment, but only in a case where the court makes an order for committal.\n\n\nUpdated: Friday, 2 October 2020",
  "metadata": {
    "source": "Family Procedure Rules – Practice Directions",
    "ref": "PD 37A",
    "title": "Practice Direction 37A – Applications and Proceedings in Relation to Contempt of Court",
    "url": "https://www.justice.gov.uk/courts/procedure-rules/family/practice_directions/practice-direction-37a-applications-and-proceedings-in-relation-to-contempt-of-court",
    "status": "Active",
    "scraped": "2026-06-10",
    "licence": "Open Government Licence v3.0"
  }
}