{
  "chunk_id": "s1__chunk001",
  "source_file": "raw/legislation/matrimonial_causes_act_1973/s1.md",
  "layer": "layer1",
  "chunk_index": 1,
  "total_chunks": 2,
  "token_count": 163,
  "text": "**(8)** In a particular case the court dealing with the case may by order shorten the period that would otherwise be applicable for the purposes of subsection (4)(b) or (5).\n\n**(9)** A statutory instrument containing an order under subsection (6) may not be made unless a draft of the instrument has been laid before and approved by a resolution of each House of Parliament.\n\n**(10)** Without prejudice to the generality of section 75 of the Courts Act 2003, Family Procedure Rules may make provision as to the procedure for an application under subsection (1) by both parties to a marriage to become an application by one party to the marriage only (including provision for a statement made under subsection (2) in connection with the application to be treated as made by one party to the marriage only).",
  "metadata": {
    "source": "Matrimonial Causes Act 1973 (c. 18)",
    "act": "Matrimonial Causes Act 1973",
    "section": "1",
    "title": "Section 1",
    "url": "https://www.legislation.gov.uk/ukpga/1973/18/section/1",
    "version": "Latest available (Revised) — valid from 2024-08-02",
    "scraped": "2026-06-10",
    "licence": "Open Government Licence v3.0"
  }
}