{
  "chunk_id": "s21__chunk000",
  "source_file": "raw/legislation/matrimonial_causes_act_1973/s21.md",
  "layer": "layer1",
  "chunk_index": 0,
  "total_chunks": 2,
  "token_count": 440,
  "text": "# Section 21\n\n## Part II Financial Relief for Parties to Marriage and Children of Family\n\n\n### Financial provision and property adjustment orders\n\n\n#### 21 Financial provision and property adjustment orders.\n\n\n**(1)** The financial provision orders for the purposes of this Act are the orders for periodical or lump sum provision available (subject to the provisions of this Act) under section 23 below for the purpose of adjusting the financial position of the parties to a marriage and any children of the family in connection with proceedings for divorce, nullity of marriage or judicial separation and under section 27(6) below on proof of neglect by one party to a marriage to provide, or to make a proper contribution towards, reasonable maintenance for the other or a child of the family, that is to say—\n- **(a)** any order for periodical payments in favour of a party to a marriage under section 23(1)(a) or 27(6)(a) or in favour of a child of the family under section 23(1)(d), (2) or (4) or 27(6)(d);\n- **(b)** any order for secured periodical payments in favour of a party to a marriage under section 23(1)(b) or 27(6)(b) or in favour of a child of the family under section 23(1)(e), (2) or (4) or 27(6)(e); and\n- **(c)** any order for lump sum provision in favour of a party to a marriage under section 23(1)(c) or 27(6)(c) or in favour of a child of the family under section 23(1)(f), (2) or (4) or 27(6)(f);\n\n and references in this Act (except in paragraphs 17(1) and 23 of Schedule 1 below) to periodical payments orders, secured periodical payments orders, and orders for the payment of a lump sum are references to all or some of the financial provision orders requiring the sort of financial provision in question according as the context of each reference may require.",
  "metadata": {
    "source": "Matrimonial Causes Act 1973 (c. 18)",
    "act": "Matrimonial Causes Act 1973",
    "section": "21",
    "title": "Section 21",
    "url": "https://www.legislation.gov.uk/ukpga/1973/18/section/21",
    "version": "Latest available (Revised) — valid from 2024-08-02",
    "scraped": "2026-06-10",
    "licence": "Open Government Licence v3.0"
  }
}