{
  "chunk_id": "FPR_Part_4__chunk001",
  "source_file": "raw/legislation/fpr_2010/FPR_Part_4.md",
  "layer": "layer1",
  "chunk_index": 1,
  "total_chunks": 4,
  "token_count": 484,
  "text": "F4 Words in rule 4.1(8) inserted (6.4.2012) by The Family Procedure (Amendment) Rules 2012 (S.I. 2012/679) , rules 1 , 4 (with rule 30 )\n\n\n### Court officer's power to refer to the court E+W\n\n\n4.2. Where a step is to be taken by a court officer—\n\n\n### Court's power to make order of its own initiative E+W\n\n\n4.3. —(1) Except where an enactment provides otherwise, the court may exercise its powers on an application or of its own initiative. (Part 18 sets out the procedure for making an application.)\n\n\n(2) [ F5 Subject to rule 29.17, where ] the court proposes to make an order of its own initiative—\n\n\n(3) Where the court proposes—\n\n\nit must give each party likely to be affected by the order at least 5 days' notice of the hearing.\n\n\n(4) The court may make an order of its own initiative without hearing the parties or giving them an opportunity to make representations.\n\n\n(5) Where the court has made an order under paragraph (4)—\n\n\n(6) An application under paragraph (5)(a) must be made—\n\n\n(7) If [ F6 the court ] of its own initiative strikes out a statement of case or dismisses an application (including an application for permission to appeal) and it considers that the application is totally without merit—\n\n\nTextual Amendments\n\n\nF5 Words in rule 4.3(2) substituted (22.4.2014) by The Family Procedure (Amendment No.3) Rules 2013 (S.I. 2013/3204) , rules 1 , 6(a) (with rule 137 ); S.I. 2014/954 , art. 2\n\n\nF6 Words in rule 4.3(7) substituted (22.4.2014) by The Family Procedure (Amendment No.3) Rules 2013 (S.I. 2013/3204) , rules 1 , 6(b) (with art. 137 ); S.I. 2014/954 , art. 2\n\n\n### Power to strike out a statement of case E+W",
  "metadata": {
    "source": "The Family Procedure Rules 2010 (SI 2010/2955)",
    "part": 4,
    "title": "Part 4 — General Case Management Powers",
    "url": "https://www.legislation.gov.uk/uksi/2010/2955/part/4",
    "version": "Latest available (Revised)",
    "scraped": "2026-06-10",
    "licence": "Open Government Licence v3.0"
  }
}