{
  "chunk_id": "FPR_Part_9__chunk000",
  "source_file": "raw/legislation/fpr_2010/FPR_Part_9.md",
  "layer": "layer1",
  "chunk_index": 0,
  "total_chunks": 45,
  "token_count": 486,
  "text": "# Part 9 — Applications for a Financial Remedy\n\n## PART 9 E+W APPLICATIONS FOR A FINANCIAL REMEDY\n\n\n### CHAPTER 1 E+W APPLICATION AND INTERPRETATION\n\n\n### [ F1 Application E+W\n\n\n9.1. — (1) The rules in this Part apply to an application for a financial remedy.\n\n\n(2) This Part is subject to any provision made by or pursuant to Part 41 (proceeding by electronic means).\n\n\n(“Financial remedy” and “financial order” are defined in rule 2.3.) ]\n\n\nTextual Amendments\n\n\nF1 Rule 9.1 substituted (6.4.2020) by The Family Procedure (Amendment) Rules 2020 (S.I. 2020/135) , rules 1 , 9\n\n\n### Application of Magistrates' Courts Rules 1981 E+W\n\n\nF2 9.2. . . . . . . . . . . . . . . . . . . . . . . . . . . . . . . . .\n\n\nTextual Amendments\n\n\nF2 Rule 9.2 omitted (22.4.2014) by virtue of The Family Procedure (Amendment No. 2) Rules 2014 (S.I. 2014/667) , rules 1 , 7 (with rule 45 )\n\n\n### Interpretation E+W\n\n\n9.3. —(1) In this Part—\n\n\n“ avoidance of disposition order ” means—\n\n(a)\n\nin proceedings under the 1973 Act, an order under section 37(2)(b) or (c) of that Act;\n\n(b)\n\nin proceedings under the 1984 Act, an order under section 23(2)(b) or 23(3) of that Act M1 ;\n\n(c)\n\nin proceedings under Schedule 5 to the 2004 Act, an order under paragraph 74(3) or (4); or\n\n(d)\n\nin proceedings under Schedule 7 to the 2004 Act, an order under paragraph 15(3) or (4);\n\n\n“ the Board ” means the Board of the Pension Protection Fund;\n\n\n[ F3 “fast-track procedure” means the procedure set out in Chapter 5; ]\n\n\n“ FDR appointment ” means a Financial Dispute Resolution appointment in accordance with rule 9.17;",
  "metadata": {
    "source": "The Family Procedure Rules 2010 (SI 2010/2955)",
    "part": 9,
    "title": "Part 9 — Applications for a Financial Remedy",
    "url": "https://www.legislation.gov.uk/uksi/2010/2955/part/9",
    "version": "Latest available (Revised)",
    "scraped": "2026-06-10",
    "licence": "Open Government Licence v3.0"
  }
}