{
  "chunk_id": "FPR_Part_25__chunk003",
  "source_file": "raw/legislation/fpr_2010/FPR_Part_25.md",
  "layer": "layer1",
  "chunk_index": 3,
  "total_chunks": 9,
  "token_count": 491,
  "text": "### When to apply for the court’s permission E+W\n\n\n[ F11 25.6. Unless the court directs otherwise, parties must apply for the court’s permission as mentioned in section 13(1), (3) or (5) of the 2014 Act or rule 25.4(2) as soon as possible and—\n\n\nTextual Amendments\n\n\nF11 Rule 25.6 substituted (22.4.2014) by The Family Procedure (Amendment No. 3) Rules 2014 (S.I. 2014/843) , rules 1 , 48\n\n\nF12 Word in rule 25.6(e) substituted (6.4.2022) by The Family Procedure (Amendment) Rules 2022 (S.I. 2022/44) , rules 1(3)(a) , 27(a) (with rule 29 ); S.I. 2022/283 , reg. 2\n\n\nF13 Word in rule 25.6(e) substituted (6.4.2022) by The Family Procedure (Amendment) Rules 2022 (S.I. 2022/44) , rules 1(3)(a) , 27(b) (with rule 29 ); S.I. 2022/283 , reg. 2\n\n\n### What an application notice requesting the court’s permission must include E+W\n\n\n25.7. — (1) Part 18 applies to an application for the court’s permission as mentioned in [ F14 section 13(1), (3) or (5) of the 2014 Act or ] rule 25.4 [ F14 (2) ] .\n\n\n(2) In any proceedings—\n\n\n(3) In children proceedings, an application notice requesting the court’s permission as mentioned in [ F16 section 13(1), (3) or (5) of the 2014 Act ] must, in addition to the matters specified in paragraph (2)(a), state the questions which the expert is to be required to answer.\n\n\nTextual Amendments\n\n\nF14 Words in rule 25.7(1) inserted (22.4.2014) by The Family Procedure (Amendment No. 3) Rules 2014 (S.I. 2014/843) , rules 1 , 49(a)",
  "metadata": {
    "source": "The Family Procedure Rules 2010 (SI 2010/2955)",
    "part": 25,
    "title": "Part 25 — Experts and Assessors",
    "url": "https://www.legislation.gov.uk/uksi/2010/2955/part/25",
    "version": "Latest available (Revised)",
    "scraped": "2026-06-10",
    "licence": "Open Government Licence v3.0"
  }
}