{
  "chunk_id": "FPR_Part_9__chunk024",
  "source_file": "raw/legislation/fpr_2010/FPR_Part_9.md",
  "layer": "layer1",
  "chunk_index": 24,
  "total_chunks": 45,
  "token_count": 491,
  "text": "### [ F63 Consideration of the application at the first hearing E+W\n\n\n9.20. — (1) If the court is able to determine the application at the first hearing, it must do so unless it considers that there are good reasons not to do so.\n\n\n(2) Paragraphs (3) to (7) apply where the court does not determine the application at the first hearing.\n\n\n(3) The court may give directions relating to—\n\n\n(4) The court may use the first hearing or part of it as a FDR appointment.\n\n\n(5) Where the court uses the first hearing or part of it as a FDR appointment, rule 9.17 applies with these modifications—\n\n\n“ (3) At the first hearing, the applicant must produce to the court all offers and proposals and responses to them. ” ; and\n\n\n(6) The court may direct that the application be referred to a FDR appointment.\n\n\n(7) If the court decides that a referral to a FDR appointment is not appropriate it must direct one or more of the following—\n\n\n[ F65 (Rule 3.4 makes provision in relation to cases in which the court considers non-court dispute resolution is appropriate.) ] ]\n\n\nTextual Amendments\n\n\nF63 Rule 9.20 substituted (4.6.2018) by The Family Procedure (Amendment) Rules 2018 (S.I. 2018/440) , rules 1 , 11\n\n\nF64 Words in rule 9.20(5)(b) substituted (6.7.2020) by The Family Procedure (Amendment) Rules 2020 (S.I. 2020/135) , rules 1 , 11\n\n\nF65 Words in rule 9.20(7) substituted (29.4.2024) by The Family Procedure (Amendment No. 2) Rules 2023 (S.I. 2023/1324) , rules 1(3)(b) , 17\n\n\n### Who the respondent is on an application under section 20 or section 20A of the 1978 Act M16 or Part 6 of Schedule 6 to the 2004 Act E+W\n\n\n9.21. In relation to proceedings set out in column 1 of the following table, column 2 sets out who the respondents to those proceedings will be.\n\n\nTextual Amendments",
  "metadata": {
    "source": "The Family Procedure Rules 2010 (SI 2010/2955)",
    "part": 9,
    "title": "Part 9 — Applications for a Financial Remedy",
    "url": "https://www.legislation.gov.uk/uksi/2010/2955/part/9",
    "version": "Latest available (Revised)",
    "scraped": "2026-06-10",
    "licence": "Open Government Licence v3.0"
  }
}