{
  "chunk_id": "FPR_Part_8__chunk008",
  "source_file": "raw/legislation/fpr_2010/FPR_Part_8.md",
  "layer": "layer1",
  "chunk_index": 8,
  "total_chunks": 12,
  "token_count": 499,
  "text": "### Service of the application E+W\n\n\n8.31. —(1) The court will serve a copy of the application on—\n\n\nunless the court directs that the applicant must do so.\n\n\n(2) Where service is effected by the applicant, the applicant must file a certificate of service.\n\n\n[ F14 (Part 6 of these Rules makes provision in relation to the method of service, and includes rule 6.23A which specifies how service is to be effected on a person where there are reasonable grounds to believe that person is residing in a refuge.) ]\n\n\nTextual Amendments\n\n\nF14 Words in rule 8.31 inserted (13.1.2025) by The Family Procedure (Amendment) Rules 2024 (S.I. 2024/1016) , rules 1(3)(b) , 5\n\n\nMarginal Citations\n\n\nM8 Paragraph 1 of Schedule 7 to the Family Law Act 1996 was amended by section 82 of and paragraphs 16(1) and (2) of Schedule 9 to the Civil Partnership Act 2004 and article 2 of and paragraph 10(b)(i) of the Schedule to the Housing Act 1996 (Consequential Amendments) Order 1997 (S.I. 1997/74) .\n\n\n### Who the parties are E+W\n\n\n8.32. The court will direct that a landlord be made a party to the proceedings where the landlord requests to be one.\n\n\n### Orders for disclosure E+W\n\n\n8.33. Any party may apply to the court under rule 21.2 for an order that any person must attend an appointment before the court and produce any documents that are specified or described in the order.\n\n\n### Injunctions E+W\n\n\n8.34. —(1) The court may grant an injunction (GL) only if the injunction (GL) is ancillary or incidental to the assistance sought by the applicant.\n\n\n(2) Applications for injunctive relief must be made in accordance with the procedure in rule 20.4 (how to apply for an interim remedy) and the provisions of rule 20.5 (interim injunction (GL) to cease if application is stayed (GL) ) apply accordingly.\n\n\n### CHAPTER 8 E+W APPLICATIONS FOR ORDERS PREVENTING AVOIDANCE UNDER SECTION 32L OF THE CHILD SUPPORT ACT 1991\n\n\n### Scope of this Chapter E+W",
  "metadata": {
    "source": "The Family Procedure Rules 2010 (SI 2010/2955)",
    "part": 8,
    "title": "Part 8 — Procedure for Miscellaneous Applications",
    "url": "https://www.legislation.gov.uk/uksi/2010/2955/part/8",
    "version": "Latest available (Revised)",
    "scraped": "2026-06-10",
    "licence": "Open Government Licence v3.0"
  }
}