{
  "chunk_id": "FPR_Part_27__chunk001",
  "source_file": "raw/legislation/fpr_2010/FPR_Part_27.md",
  "layer": "layer1",
  "chunk_index": 1,
  "total_chunks": 8,
  "token_count": 504,
  "text": "F2 Words in rule 27.2(1) substituted (22.4.2014) by The Family Procedure (Amendment No. 2) Rules 2014 (S.I. 2014/667) , rules 1 , 19(b) (with rule 45 )\n\n\nF3 Words in rule 27.2 substituted (6.4.2020) by The Family Procedure (Amendment) Rules 2020 (S.I. 2020/135) , rules 1 , 27\n\n\nF4 Word in rule 27.2(5)(a) inserted (22.4.2014) by The Family Procedure (Amendment No. 2) Rules 2014 (S.I. 2014/667) , rules 1 , 19(c)(i) (with rule 45 )\n\n\nF5 Word in rule 27.2(5)(b) inserted (22.4.2014) by The Family Procedure (Amendment No. 2) Rules 2014 (S.I. 2014/667) , rules 1 , 19(c)(ii) (with rule 45 )\n\n\nF6 Word in rule 27.2(7) inserted (22.4.2014) by The Family Procedure (Amendment No. 2) Rules 2014 (S.I. 2014/667) , rules 1 , 19(d) (with rule 45 )\n\n\nF7 Rule 27.2(10) omitted (22.4.2014) by virtue of The Family Procedure (Amendment No. 2) Rules 2014 (S.I. 2014/667) , rules 1 , 19(e) (with rule 45 )\n\n\n### Attendance at hearing or directions appointment E+W\n\n\n27.3. Unless the court directs otherwise, a party shall attend a hearing or directions appointment of which that party has been given notice.\n\n\n### Proceedings in the absence of a party E+W\n\n\n27.4. —(1) Proceedings or any part of them shall take place in the absence of any party, including a party who is a child, if—\n\n\nand when considering the interests of a child under sub-paragraph (a) the court shall give the children's guardian, the solicitor for the child and, if of sufficient understanding and the court thinks it appropriate, the child, an opportunity to make representations.",
  "metadata": {
    "source": "The Family Procedure Rules 2010 (SI 2010/2955)",
    "part": 27,
    "title": "Part 27 — Hearings and Directions Appointments",
    "url": "https://www.legislation.gov.uk/uksi/2010/2955/part/27",
    "version": "Latest available (Revised)",
    "scraped": "2026-06-10",
    "licence": "Open Government Licence v3.0"
  }
}