{
  "chunk_id": "sfo_vol1__004__order_21_financial_remedy_order__chunk007",
  "source_file": "raw/standard_orders/sfo_vol1__004__order_21_financial_remedy_order.md",
  "layer": "layer1",
  "chunk_index": 7,
  "total_chunks": 61,
  "token_count": 444,
  "text": "Declaration of intention not to seek a variation of a periodical payments order\n\n(receiving party)\n\nThe [applicant] / [respondent] declares that it is not their intention to seek an increase of the order for periodical payments at paragraph [para number] below for themselves [and the children of the family] [for a period of at least [number] years from the date of this order] / [for so long as the [respondent] / [applicant] does not [earn] / [become entitled to drawings] in excess of £[amount] gross [per annum] [[RPI] / [CPI] index-linked]] / [except [in exceptional circumstances] / [in the event that [he] / [she] becomes unintentionally unemployed through no action or fault of their own] / [in the event that [he] / [she] suffers from severe illness or disability rendering them unable to work]].\n\nDeclaration of intention not to seek a variation of a periodical payments order\n\n(paying party)\n\nThe [respondent] / [applicant] declares that it is not their intention to seek a decrease of the order for periodical payments at paragraph [para number] below in favour of the [applicant] / [respondent] [and the children of the family] [for a period of at least [number] years from the date of this order] / [for so long as the [respondent] / [applicant] does not [earn] / [become entitled to drawings of] in excess of £[amount] gross [per annum] [[RPI] / [CPI] index-linked]] / [for so long as the [applicant] / [respondent] does not [earn] / [become entitled to drawings of] less than £[amount] gross [per annum] [[RPI] [CPI] index-linked]] / [except in exceptional circumstances] / [unless there has been a material change in their or the [applicant’s] / [respondent’s] financial circumstances].\n\nDeclaration of intention to limit claims under the Inheritance (Provision for Family and Dependants) Act 1975",
  "metadata": {
    "source": "Standard Family Orders — Volume 1: Financial Remedies (May 2026)",
    "title": "In the Family Court\t\tCase No: [Case number]",
    "order_number": "order_21_financial_remedy_order",
    "volume": 1,
    "parent_document": "Standard Family Orders — Volume 1: Financial Remedies (May 2026)",
    "parent_slug": "sfo_vol1",
    "section_index": 4,
    "source_filename": "Order 2.1 - Financial Remedy Order.docx",
    "source_page": "https://www.judiciary.uk/guidance-and-resources/update-from-mr-justice-peel-judge-in-charge-of-the-standard-orders/",
    "url": "https://www.judiciary.uk/wp-content/uploads/2026/05/SFO-Volume-1-05.26.zip",
    "scrape_date": "2026-06-10",
    "licence": "Open Government Licence v3.0",
    "content_type": "standard_order",
    "jurisdiction": "England and Wales"
  }
}