{
  "chunk_id": "sfo_vol2__101__order_80_public_law_case_management_directions_and_orders_precedent_library__chunk011",
  "source_file": "raw/standard_orders/sfo_vol2__101__order_80_public_law_case_management_directions_and_orders_precedent_library.md",
  "layer": "layer1",
  "chunk_index": 11,
  "total_chunks": 29,
  "token_count": 497,
  "text": "The local authority must deliver this order and a statement of service to [police force] as soon as is practicable.\n\nThis exclusion requirement having been made [without notice to [name of excluded person]] [at a hearing at which [name of excluded person] has not attended], the court will consider whether the order should be varied or discharged at a hearing at the Family Court sitting at [court name] on [date] at [time] allowing [number] hours.\n\n[Name of excluded person] has the right to apply to the court at any time to vary or discharge this exclusion requirement.\n\nExperts\n\nThe application by [name] for permission to instruct [name of expert] is adjourned pending compliance with Part 25C Family Procedure Rules 2010. Upon compliance the court will consider the application [at a hearing to be listed] / [on paper].\n\n[Name(s)/party/ies] [is] / [are] given permission to instruct [name of expert], [insert discipline], as a single joint expert to assess [names of people being assessed including specifying any children]. The report of the expert shall be filed at court and served on the parties by 4.00pm on [date]. Directions for implementation of this expert instruction are contained in the schedule to this order. The cost of such report shall be paid by the parties equally.\n\nPermission is given to [name] to instruct the following experts as single joint experts:\n\n[Name of expert], [insert discipline] to assess [names of people being assessed including specifying any children], whose report shall be filed at court and served on the parties by 4.00pm on [date].\n\n[etc.].\n\nDirections for implementation of these expert instructions are contained in the schedule to this order. The cost of such report shall be paid by the parties equally.\n\nUnless the experts are agreed there shall be an expert’s discussion to be arranged by the solicitor for the child[ren] which must occur not later than [date not later than 15 business days after the reports have been filed and served]:\n\nThe draft agenda for the expert’s discussion shall be circulated by the child[ren]’s solicitor not less than 5 working days prior to the meeting, which shall be agreed by the parties and sent to the expert not less than 2 working days before the discussion.\n\nThe discussion shall be chaired by [the child[ren]’s solicitor] / [name].",
  "metadata": {
    "source": "Standard Family Orders — Volume 2: Children and Other Orders (May 2026)",
    "title": "PRECEDENT LIBRARY OF PUBLIC LAW CASE MANAGEMENT DIRECTIONS AND ORDERS",
    "order_number": "order_80_public_law_case_management_directions_and_orders_precedent_library",
    "volume": 2,
    "parent_document": "Standard Family Orders — Volume 2: Children and Other Orders (May 2026)",
    "parent_slug": "sfo_vol2",
    "section_index": 101,
    "source_filename": "Order 8.0 - Public Law Case Management Directions and Orders Precedent Library.docx",
    "source_page": "https://www.judiciary.uk/guidance-and-resources/update-from-mr-justice-peel-judge-in-charge-of-the-standard-orders/",
    "url": "https://www.judiciary.uk/wp-content/uploads/2026/05/SFO-Volume-2-05.26-1.zip",
    "scrape_date": "2026-06-10",
    "licence": "Open Government Licence v3.0",
    "content_type": "standard_order",
    "jurisdiction": "England and Wales"
  }
}