{
  "chunk_id": "sfo_vol2__026__order_1323_abduction_γçô_wardship_directions_order_on_notice_γçô_pakistan_protoc__chunk004",
  "source_file": "raw/standard_orders/sfo_vol2__026__order_1323_abduction_γçô_wardship_directions_order_on_notice_γçô_pakistan_protoc.md",
  "layer": "layer1",
  "chunk_index": 4,
  "total_chunks": 6,
  "token_count": 479,
  "text": "IT IS ORDERED THAT:\n\nThe child[ren] shall remain [a] ward[s] of this court during their minority or until further order.\n\nThe respondent [respondent name] shall return the child[ren] forthwith to England and Wales.\n\nEvery person within the jurisdiction of this court who is in a position to do so shall co-operate in assisting and securing the immediate return to England and Wales of child[ren].\n\nIn a case where assistance is sought from the International Family Justice Office  the applicant’s solicitors shall email copies of this order to the Office of the Head of International Family Justice at the Royal Courts of Justice, The Strand, London WC2A 2LL, United Kingdom (DX4450 Strand RCJ; IFJOffice@justice.gov.uk) [and in a case where assistance is sought from Foreign and Commonwealth Office to either: (a) the Child Policy Unit, Foreign and Commonwealth Office, King Charles Street, London SW1A 2AH, Consular.ChildrensPolicyOfficer@fco.gov.uk; or (b) where the case concerns either Forced Marriage or Female Genital Mutilation, the Forced Marriage Unit FMU@fcdo.gov.uk].\n\nThe matter shall be listed for directions [within 7 days of the return of the child[ren] to England and Wales] / [at 10:30am on [date]].\n\n(where assistance from the fcdo will be sought and there is no good reason for the fcdo not having been provisionally contacted in advance)  The applicant is directed to contact the [Child Policy Unity within the Consular Directorate of the Foreign, Commonwealth and Development Office] / [(if the case concerns either forced marriage or female genital mutilation) Forced Marriage Unit] to ascertain, in advance of the next hearing, whether the FCDO is in a position to assist and, if so, in what way.\n\nPermission is granted to [the applicant] / [insert other appropriate party] to disclose a copy of this Order [and [insert any other relevant appropriate documents]] to the FCDO [Child Policy Unit] / [Forced Marriage Unit].\n\nPermission is granted to the Foreign, Commonwealth and Development Office of the United Kingdom to share the information disclosed to them in accordance with paragraph [para number] above with [insert named bodies/persons] [and any other relevant agency].",
  "metadata": {
    "source": "Standard Family Orders — Volume 2: Children and Other Orders (May 2026)",
    "title": "Order",
    "order_number": "order_1323_abduction_γçô_wardship_directions_order_on_notice_γçô_pakistan_protoc",
    "volume": 2,
    "parent_document": "Standard Family Orders — Volume 2: Children and Other Orders (May 2026)",
    "parent_slug": "sfo_vol2",
    "section_index": 26,
    "source_filename": "Order 13.23 - Abduction ΓÇô Wardship Directions Order (On Notice ΓÇô Pakistan Protocol).docx",
    "source_page": "https://www.judiciary.uk/guidance-and-resources/update-from-mr-justice-peel-judge-in-charge-of-the-standard-orders/",
    "url": "https://www.judiciary.uk/wp-content/uploads/2026/05/SFO-Volume-2-05.26-1.zip",
    "scrape_date": "2026-06-10",
    "licence": "Open Government Licence v3.0",
    "content_type": "standard_order",
    "jurisdiction": "England and Wales"
  }
}